MANIFEST.in
README.rst
setup.cfg
setup.py
Presser.egg-info/PKG-INFO
Presser.egg-info/SOURCES.txt
Presser.egg-info/dependency_links.txt
Presser.egg-info/pbr.json
Presser.egg-info/requires.txt
Presser.egg-info/top_level.txt
presser/__init__.py
presser/exceptions.py
presser/presser.py