Metadata-Version: 1.1
Name: Presser
Version: 0.1.8
Summary: Extracts data from vine, in lieu of an API
Home-page: https://github.com/ladyrassilon/presser
Author: Gemma Hentsch
Author-email: contact@halfapenguin.com
License: GNU GPL v3.0
Download-URL: https://github.com/ladyrassilon/presser/archive/
Keywords: scraping,vine
Platform: UNKNOWN
Classifier: Development Status :: 4 - Beta
Classifier: Programming Language :: Python :: 3.3
Classifier: Programming Language :: Python :: 3.4
Classifier: Programming Language :: Python :: 2.7
Classifier: Programming Language :: Python :: Implementation :: CPython
Classifier: Programming Language :: Python :: Implementation :: PyPy
Classifier: Programming Language :: Python
Classifier: Intended Audience :: Developers
Requires: beautifulsoup4(>=4.3.2)
Requires: requests(>=2.4.0)
Requires: mock(>=1.0.1)
Requires: coverage(>=3.7.1)
Requires: nose(>=1.3.4)
Requires: PyExecJS(>=1.0.4)
Requires: responses(>=0.2.2)
